jiff/_lowlevel.cpython-311-darwin.so
jiff/__init__.py
jiff-0.2.0.dist-info/RECORD
jiff-0.2.0.dist-info/WHEEL
jiff-0.2.0.dist-info/METADATA
jiff-0.2.0.dist-info/license_files/LICENSE
