Metadata-Version: 2.3
Name: jiff
Version: 0.2.0
License-File: LICENSE
Summary: Python bindings to the Jiff datetime library
Author-email: Tyler Kennedy <tk@tkte.ch>
Requires-Python: >=3.10
Project-URL: Repository, https://github.com/tktech/pyjiff
